pypassword/__init__.py
pypassword/pypassword.py
tests/__init__.py
tests/test_generator.py
pypassword-0.1.2.dist-info/LICENSE
pypassword-0.1.2.dist-info/METADATA
pypassword-0.1.2.dist-info/WHEEL
pypassword-0.1.2.dist-info/top_level.txt
pypassword-0.1.2.dist-info/RECORD
